[
    {
        "v": "RT001"
    },
    {
        "v": "D"
    },
    {
        "v": "SARI KUSUMA DEWI"
    },
    {
        "v": "D4"
    },
    {
        "v": "Date(2024,0,15)",
        "f": "15/1/2024"
    },
    null,
    null,
    null,
    null,
    null,
    null,
    null,
    null,
    null,
    null,
    null,
    {
        "v": "Date(2025,3,8)",
        "f": "8/4/2025"
    },
    null,
    null,
    null,
    null,
    null,
    {
        "v": "Date(2025,7,6)",
        "f": "6/8/2025"
    },
    null,
    null,
    null,
    null,
    null,
    {
        "v": "Date(2025,11,3)",
        "f": "3/12/2025"
    },
    null,
    null,
    {
        "v": "√"
    },
    {
        "v": "√"
    },
    {
        "v": "√"
    },
    null,
    null,
    null,
    null,
    null,
    null,
    null,
    null,
    null,
    null,
    null,
    null,
    null,
    null,
    null,
    null,
    null,
    null,
    null,
    null,
    null,
    null,
    null,
    null,
    null,
    null,
    null,
    null,
    null,
    {
        "v": null
    }
]